{
  "type": "Feature",
  "properties": {
    "gn:admin1_code":"10",
    "gn:asciiname":"Koumbou",
    "gn:country_code":"MR",
    "gn:dem":21,
    "gn:feature_class":"P",
    "gn:feature_code":"PPL",
    "gn:name":"Koumbou",
    "gn:population":0,
    "gn:timezone":"Africa/Nouakchott",
    "iso:country":"MR",
    "wof:name":"Koumbou",
    "wof:placetype":"locality"
},
  "geometry": {"coordinates":[-12.78211,15.148],"type":"Point"}
}