{
  "type": "Feature",
  "properties": {
    "gn:admin1_code":"01",
    "gn:asciiname":"Kataouane",
    "gn:cc2":"MR",
    "gn:country_code":"MR",
    "gn:dem":300,
    "gn:feature_class":"P",
    "gn:feature_code":"PPL",
    "gn:name":"Ka\u1e6daou\u00e2ne",
    "gn:population":0,
    "gn:timezone":"Africa/Nouakchott",
    "iso:country":"MR",
    "name:und_x_variant":[
        "Kataouan",
        "Ka\u1e6daou\u00e2ne"
    ],
    "wof:name":"Kataouane",
    "wof:placetype":"locality"
},
  "geometry": {"coordinates":[-6.49889,16.06889],"type":"Point"}
}