{
  "type": "Feature",
  "properties": {
    "gn:admin1_code":"05",
    "gn:asciiname":"Adabai Deili",
    "gn:country_code":"MR",
    "gn:dem":39,
    "gn:feature_class":"P",
    "gn:feature_code":"PPL",
    "gn:name":"Adaba\u00ef De\u00efli",
    "gn:population":0,
    "gn:timezone":"Africa/Nouakchott",
    "iso:country":"MR",
    "wof:name":"Adabai Deili",
    "wof:placetype":"locality"
},
  "geometry": {"coordinates":[-13.83094,16.40949],"type":"Point"}
}