{
  "type": "Feature",
  "properties": {
    "gn:admin1_code":"07",
    "gn:asciiname":"Oujeft",
    "gn:cc2":"MR",
    "gn:country_code":"MR",
    "gn:dem":219,
    "gn:feature_class":"P",
    "gn:feature_code":"PPL",
    "gn:name":"Oujeft",
    "gn:population":0,
    "gn:timezone":"Africa/Nouakchott",
    "iso:country":"MR",
    "name:und_x_variant":[
        "Aoujeft",
        "Oujefte",
        "Oujeft"
    ],
    "wof:name":"Oujeft",
    "wof:placetype":"locality"
},
  "geometry": {"coordinates":[-13.05944,19.96222],"type":"Point"}
}