{
  "type": "Feature",
  "properties": {
    "gn:admin1_code":"07",
    "gn:asciiname":"Oujeft",
    "gn:cc2":"MR",
    "gn:country_code":"MR",
    "gn:dem":219,
    "gn:feature_class":"P",
    "gn:feature_code":"PPL",
    "gn:name":"Oujeft",
    "gn:population":0,
    "gn:timezone":"Africa/Nouakchott",
    "iso:country":"MR",
    "name:ara_x_preferred":[
        "\u0627\u0648\u062c\u0641\u062a"
    ],
    "name:bel_x_preferred":[
        "\u0410\u045e\u0436\u044d\u0444\u0442"
    ],
    "name:fra_x_preferred":[
        "Aoujeft"
    ],
    "name:ita_x_preferred":[
        "Aoujeft"
    ],
    "name:msa_x_preferred":[
        "Aoujeft"
    ],
    "name:pol_x_preferred":[
        "Aud\u017cift"
    ],
    "name:ron_x_preferred":[
        "Aoujeft"
    ],
    "name:rus_x_preferred":[
        "\u0410\u0443\u0436\u0435\u0444\u0442"
    ],
    "name:spa_x_preferred":[
        "Aoujeft"
    ],
    "name:swe_x_preferred":[
        "Aoujeft"
    ],
    "name:und_x_variant":[
        "Oujefte",
        "Oujeft"
    ],
    "wof:lang_x_official":[
        "ara"
    ],
    "wof:lang_x_spoken":[
        "ara"
    ],
    "wof:name":"Oujeft",
    "wof:placetype":"locality"
},
  "geometry": {"coordinates":[-13.05944,19.96222],"type":"Point"}
}