{
  "type": "Feature",
  "properties": {
    "gn:admin1_code":"04",
    "gn:asciiname":"Gourel Tierno",
    "gn:country_code":"MR",
    "gn:dem":22,
    "gn:feature_class":"P",
    "gn:feature_code":"PPL",
    "gn:name":"Gourel Tierno",
    "gn:population":0,
    "gn:timezone":"Africa/Nouakchott",
    "iso:country":"MR",
    "wof:name":"Gourel Tierno",
    "wof:placetype":"locality"
},
  "geometry": {"coordinates":[-12.94501,15.37839],"type":"Point"}
}