{
  "type": "Feature",
  "properties": {
    "gn:admin1_code":"01",
    "gn:asciiname":"Saile",
    "gn:country_code":"MR",
    "gn:dem":309,
    "gn:feature_class":"P",
    "gn:feature_code":"PPL",
    "gn:name":"S\u00e2\u00efl\u00e9",
    "gn:population":0,
    "gn:timezone":"Africa/Nouakchott",
    "iso:country":"MR",
    "wof:name":"Saile",
    "wof:placetype":"locality"
},
  "geometry": {"coordinates":[-7.0894,16.476],"type":"Point"}
}