{
  "type": "Feature",
  "properties": {
    "gn:admin1_code":"02",
    "gn:asciiname":"Dabai el Izradite",
    "gn:country_code":"MR",
    "gn:dem":239,
    "gn:feature_class":"P",
    "gn:feature_code":"PPL",
    "gn:name":"Daba\u00ef el Izradite",
    "gn:population":0,
    "gn:timezone":"Africa/Nouakchott",
    "iso:country":"MR",
    "wof:name":"Dabai el Izradite",
    "wof:placetype":"locality"
},
  "geometry": {"coordinates":[-9.31846,15.51984],"type":"Point"}
}