{
  "type": "Feature",
  "properties": {
    "gn:admin1_code":"06",
    "gn:asciiname":"KeurMassene",
    "gn:country_code":"MR",
    "gn:dem":4,
    "gn:feature_class":"P",
    "gn:feature_code":"PPL",
    "gn:name":"KeurMass\u00e8ne",
    "gn:population":0,
    "gn:timezone":"Africa/Nouakchott",
    "iso:country":"MR",
    "name:und_x_variant":[
        "KeurMacene",
        "KeurMass\u00e8ne"
    ],
    "wof:name":"KeurMassene",
    "wof:placetype":"locality"
},
  "geometry": {"coordinates":[-16.21491,16.53848],"type":"Point"}
}