{
  "type": "Feature",
  "properties": {
    "gn:admin1_code":"03",
    "gn:asciiname":"Chkata",
    "gn:country_code":"MR",
    "gn:dem":181,
    "gn:feature_class":"P",
    "gn:feature_code":"PPL",
    "gn:name":"Chkata",
    "gn:population":0,
    "gn:timezone":"Africa/Nouakchott",
    "iso:country":"MR",
    "wof:name":"Chkata",
    "wof:placetype":"locality"
},
  "geometry": {"coordinates":[-11.01311,15.28695],"type":"Point"}
}