{
  "type": "Feature",
  "properties": {
    "gn:admin1_code":"10",
    "gn:asciiname":"Oumm Tahala",
    "gn:country_code":"MR",
    "gn:dem":122,
    "gn:feature_class":"P",
    "gn:feature_code":"PPL",
    "gn:name":"Oumm Tahala",
    "gn:population":0,
    "gn:timezone":"Africa/Nouakchott",
    "iso:country":"MR",
    "name:und_x_variant":[
        "Moutahala",
        "Oumm Tahala"
    ],
    "wof:name":"Oumm Tahala",
    "wof:placetype":"locality"
},
  "geometry": {"coordinates":[-11.90426,15.45798],"type":"Point"}
}