{
  "type": "Feature",
  "properties": {
    "gn:admin1_code":"04",
    "gn:asciiname":"Beilougue Demounde",
    "gn:country_code":"MR",
    "gn:dem":54,
    "gn:feature_class":"P",
    "gn:feature_code":"PPL",
    "gn:name":"Be\u00eflougu\u00e9 D\u00e9mound\u00e9",
    "gn:population":0,
    "gn:timezone":"Africa/Nouakchott",
    "iso:country":"MR",
    "wof:name":"Beilougue Demounde",
    "wof:placetype":"locality"
},
  "geometry": {"coordinates":[-12.69132,15.66988],"type":"Point"}
}