{
  "type": "Feature",
  "properties": {
    "gn:admin1_code":"04",
    "gn:asciiname":"Beilougue Bolol",
    "gn:country_code":"MR",
    "gn:dem":55,
    "gn:feature_class":"P",
    "gn:feature_code":"PPL",
    "gn:name":"Be\u00eflougu\u00e9 Bolol",
    "gn:population":0,
    "gn:timezone":"Africa/Nouakchott",
    "iso:country":"MR",
    "wof:lang_x_official":[
        "ara"
    ],
    "wof:lang_x_spoken":[
        "ara"
    ],
    "wof:name":"Beilougue Bolol",
    "wof:placetype":"locality"
},
  "geometry": {"coordinates":[-12.76968,15.72243],"type":"Point"}
}