{
  "type": "Feature",
  "properties": {
    "gn:admin1_code":"04",
    "gn:asciiname":"Amadou Moussa",
    "gn:country_code":"MR",
    "gn:dem":19,
    "gn:feature_class":"P",
    "gn:feature_code":"PPL",
    "gn:name":"Amadou Moussa",
    "gn:population":0,
    "gn:timezone":"Africa/Nouakchott",
    "iso:country":"MR",
    "wof:name":"Amadou Moussa",
    "wof:placetype":"locality"
},
  "geometry": {"coordinates":[-13.35878,16.16101],"type":"Point"}
}