{
  "type": "Feature",
  "properties": {
    "gn:admin1_code":"04",
    "gn:asciiname":"Chelkhat Ghiarhoum",
    "gn:country_code":"MR",
    "gn:dem":44,
    "gn:feature_class":"P",
    "gn:feature_code":"PPL",
    "gn:name":"Chelkhat Ghiarhoum",
    "gn:population":0,
    "gn:timezone":"Africa/Nouakchott",
    "iso:country":"MR",
    "name:und_x_variant":[
        "Chelrhat Rhiarhoum",
        "Chelkhat Rhiarhoum",
        "Chelkhat Ghiarhoum"
    ],
    "wof:name":"Chelkhat Ghiarhoum",
    "wof:placetype":"locality"
},
  "geometry": {"coordinates":[-12.45053,16.18519],"type":"Point"}
}