{
  "type": "Feature",
  "properties": {
    "gn:admin1_code":"05",
    "gn:asciiname":"Guidala",
    "gn:country_code":"MR",
    "gn:dem":8,
    "gn:feature_class":"P",
    "gn:feature_code":"PPL",
    "gn:name":"Guidala",
    "gn:population":0,
    "gn:timezone":"Africa/Nouakchott",
    "iso:country":"MR",
    "wof:name":"Guidala",
    "wof:placetype":"locality"
},
  "geometry": {"coordinates":[-14.44078,16.63703],"type":"Point"}
}