{
  "type": "Feature",
  "properties": {
    "gn:admin1_code":"05",
    "gn:asciiname":"Leve",
    "gn:country_code":"MR",
    "gn:dem":53,
    "gn:feature_class":"P",
    "gn:feature_code":"PPL",
    "gn:name":"L\u00e9v\u00e9",
    "gn:population":0,
    "gn:timezone":"Africa/Nouakchott",
    "iso:country":"MR",
    "wof:name":"Leve",
    "wof:placetype":"locality"
},
  "geometry": {"coordinates":[-13.67116,16.26609],"type":"Point"}
}