{
  "type": "Feature",
  "properties": {
    "gn:admin1_code":"05",
    "gn:asciiname":"Magta` Lahjar",
    "gn:country_code":"MR",
    "gn:dem":60,
    "gn:feature_class":"P",
    "gn:feature_code":"PPL",
    "gn:name":"Mag\u1e6da\u2018 La\u1e25jar",
    "gn:population":0,
    "gn:timezone":"Africa/Nouakchott",
    "iso:country":"MR",
    "name:ara_x_preferred":[
        "\u0645\u0642\u0637\u0639 \u0627\u0644\u062d\u062c\u0627\u0631"
    ],
    "name:bel_x_preferred":[
        "\u041c\u0430\u0433\u0442\u0430-\u041b\u0430\u0445\u0434\u0436\u0430\u0440"
    ],
    "name:fra_x_preferred":[
        "Magta-Lahjar"
    ],
    "name:ita_x_preferred":[
        "Maghta-Lahjar"
    ],
    "name:msa_x_preferred":[
        "Magta-Lahjar"
    ],
    "name:pol_x_preferred":[
        "Makta al-Had\u017car"
    ],
    "name:ron_x_preferred":[
        "Magta-Lahjar"
    ],
    "name:rus_x_preferred":[
        "\u041c\u0430\u0433\u0442\u0430-\u041b\u0430\u0445\u0434\u0436\u0430\u0440"
    ],
    "name:spa_x_preferred":[
        "Magta-Lahjar"
    ],
    "name:und_x_variant":[
        "Magta-lahjar",
        "Mag\u1e6da\u2018 La\u1e25jar"
    ],
    "name:urd_x_preferred":[
        "\u0645\u0642\u0637\u0639 \u0627\u0644\u062d\u062c\u0627\u0631"
    ],
    "wof:name":"Magta` Lahjar",
    "wof:placetype":"locality"
},
  "geometry": {"coordinates":[-13.0927,17.506],"type":"Point"}
}