{
  "type": "Feature",
  "properties": {
    "gn:admin1_code":"04",
    "gn:asciiname":"Roufi Aoudi",
    "gn:country_code":"MR",
    "gn:dem":13,
    "gn:feature_class":"P",
    "gn:feature_code":"PPL",
    "gn:name":"Roufi Aoudi",
    "gn:population":0,
    "gn:timezone":"Africa/Nouakchott",
    "iso:country":"MR",
    "name:und_x_variant":[
        "Rouji Aoudi",
        "Roufi Aoudi"
    ],
    "wof:name":"Roufi Aoudi",
    "wof:placetype":"locality"
},
  "geometry": {"coordinates":[-13.70896,16.15803],"type":"Point"}
}