{
  "type": "Feature",
  "properties": {
    "gn:admin1_code":"04",
    "gn:asciiname":"El Gueneiba",
    "gn:country_code":"MR",
    "gn:dem":57,
    "gn:feature_class":"P",
    "gn:feature_code":"PPL",
    "gn:name":"El Guene\u00efba",
    "gn:population":0,
    "gn:timezone":"Africa/Nouakchott",
    "iso:country":"MR",
    "wof:name":"El Gueneiba",
    "wof:placetype":"locality"
},
  "geometry": {"coordinates":[-12.25546,16.12538],"type":"Point"}
}