{
  "type": "Feature",
  "properties": {
    "gn:admin1_code":"03",
    "gn:asciiname":"Chelkhat Ould Bannahi",
    "gn:country_code":"MR",
    "gn:dem":147,
    "gn:feature_class":"P",
    "gn:feature_code":"PPL",
    "gn:name":"Chelkhat Ould Bannahi",
    "gn:population":0,
    "gn:timezone":"Africa/Nouakchott",
    "iso:country":"MR",
    "name:und_x_variant":[
        "Chelka Ould Bannahi",
        "Chelkhat Ould Bannahi"
    ],
    "wof:name":"Chelkhat Ould Bannahi",
    "wof:placetype":"locality"
},
  "geometry": {"coordinates":[-11.29439,15.9704],"type":"Point"}
}