{
  "type": "Feature",
  "properties": {
    "gn:admin1_code":"04",
    "gn:asciiname":"Chorfa",
    "gn:country_code":"MR",
    "gn:dem":67,
    "gn:feature_class":"P",
    "gn:feature_code":"PPL",
    "gn:name":"Chorfa",
    "gn:population":0,
    "gn:timezone":"Africa/Nouakchott",
    "iso:country":"MR",
    "name:cat_x_preferred":[
        "Xorfa"
    ],
    "name:ceb_x_preferred":[
        "Chorfa"
    ],
    "name:fra_x_preferred":[
        "Chorfa"
    ],
    "name:ita_x_preferred":[
        "Chorfa"
    ],
    "name:ron_x_preferred":[
        "Chorfa"
    ],
    "name:swe_x_preferred":[
        "Chorfa"
    ],
    "wof:name":"Chorfa",
    "wof:placetype":"locality"
},
  "geometry": {"coordinates":[-12.39216,15.85406],"type":"Point"}
}