{
  "type": "Feature",
  "properties": {
    "gn:admin1_code":"05",
    "gn:asciiname":"Chogar",
    "gn:country_code":"MR",
    "gn:dem":49,
    "gn:feature_class":"P",
    "gn:feature_code":"PPL",
    "gn:name":"Chog\u00e2r",
    "gn:population":0,
    "gn:timezone":"Africa/Nouakchott",
    "iso:country":"MR",
    "wof:name":"Chogar",
    "wof:placetype":"locality"
},
  "geometry": {"coordinates":[-13.66968,17.32648],"type":"Point"}
}