{
  "type": "Feature",
  "properties": {
    "gn:admin1_code":"04",
    "gn:asciiname":"Hadad",
    "gn:country_code":"MR",
    "gn:dem":45,
    "gn:feature_class":"P",
    "gn:feature_code":"PPL",
    "gn:name":"Hadad",
    "gn:population":0,
    "gn:timezone":"Africa/Nouakchott",
    "iso:country":"MR",
    "name:ita_x_preferred":[
        "Hadad"
    ],
    "name:tur_x_preferred":[
        "Hadad"
    ],
    "name:und_x_variant":[
        "Ador",
        "Haddah",
        "Hadad"
    ],
    "wof:name":"Hadad",
    "wof:placetype":"locality"
},
  "geometry": {"coordinates":[-12.94801,15.76348],"type":"Point"}
}