{
  "type": "Feature",
  "properties": {
    "gn:admin1_code":"10",
    "gn:asciiname":"Dabaili Soueli",
    "gn:country_code":"MR",
    "gn:dem":80,
    "gn:feature_class":"P",
    "gn:feature_code":"PPL",
    "gn:name":"Daba\u00efli Sou\u00e9li",
    "gn:population":0,
    "gn:timezone":"Africa/Nouakchott",
    "iso:country":"MR",
    "wof:lang_x_official":[
        "ara"
    ],
    "wof:lang_x_spoken":[
        "ara"
    ],
    "wof:name":"Dabaili Soueli",
    "wof:placetype":"locality"
},
  "geometry": {"coordinates":[-12.13804,15.80367],"type":"Point"}
}