{
  "type": "Feature",
  "properties": {
    "gn:admin1_code":"07",
    "gn:asciiname":"Mheinine",
    "gn:country_code":"MR",
    "gn:dem":279,
    "gn:feature_class":"P",
    "gn:feature_code":"PPL",
    "gn:name":"Mhe\u00efn\u00eene",
    "gn:population":0,
    "gn:timezone":"Africa/Nouakchott",
    "iso:country":"MR",
    "wof:name":"Mheinine",
    "wof:placetype":"locality"
},
  "geometry": {"coordinates":[-12.8898,20.6559],"type":"Point"}
}