{
  "type": "Feature",
  "properties": {
    "gn:admin1_code":"01",
    "gn:asciiname":"El Bekre",
    "gn:country_code":"MR",
    "gn:dem":221,
    "gn:feature_class":"P",
    "gn:feature_code":"PPL",
    "gn:name":"El Bekr\u00e9",
    "gn:population":0,
    "gn:timezone":"Africa/Nouakchott",
    "iso:country":"MR",
    "wof:name":"El Bekre",
    "wof:placetype":"locality"
},
  "geometry": {"coordinates":[-7.5472,16.1873],"type":"Point"}
}