{
  "type": "Feature",
  "properties": {
    "gn:admin1_code":"02",
    "gn:asciiname":"Soronabougou",
    "gn:country_code":"MR",
    "gn:dem":189,
    "gn:feature_class":"P",
    "gn:feature_code":"PPL",
    "gn:name":"Soronabougou",
    "gn:population":0,
    "gn:timezone":"Africa/Nouakchott",
    "iso:country":"MR",
    "wof:name":"Soronabougou",
    "wof:placetype":"locality"
},
  "geometry": {"coordinates":[-10.2596,15.52198],"type":"Point"}
}