{
  "type": "Feature",
  "properties": {
    "gn:admin1_code":"05",
    "gn:asciiname":"Garalol",
    "gn:country_code":"MR",
    "gn:dem":16,
    "gn:feature_class":"P",
    "gn:feature_code":"PPL",
    "gn:name":"Garalol",
    "gn:population":0,
    "gn:timezone":"Africa/Nouakchott",
    "iso:country":"MR",
    "wof:name":"Garalol",
    "wof:placetype":"locality"
},
  "geometry": {"coordinates":[-13.87354,16.25964],"type":"Point"}
}