{
  "type": "Feature",
  "properties": {
    "gn:admin1_code":"04",
    "gn:asciiname":"Lekseiba",
    "gn:country_code":"MR",
    "gn:dem":21,
    "gn:feature_class":"P",
    "gn:feature_code":"PPL",
    "gn:name":"Lekse\u00efba",
    "gn:population":0,
    "gn:timezone":"Africa/Nouakchott",
    "iso:country":"MR",
    "name:und_x_variant":[
        "El Kse\u00efba",
        "Leq\u00e7e\u00efba",
        "Lekse\u00efba"
    ],
    "wof:name":"Lekseiba",
    "wof:placetype":"locality"
},
  "geometry": {"coordinates":[-13.14493,16.21584],"type":"Point"}
}