{
  "type": "Feature",
  "properties": {
    "gn:admin1_code":"04",
    "gn:asciiname":"Ouechkech",
    "gn:country_code":"MR",
    "gn:dem":44,
    "gn:feature_class":"P",
    "gn:feature_code":"PPL",
    "gn:name":"Ouechkech",
    "gn:population":0,
    "gn:timezone":"Africa/Nouakchott",
    "iso:country":"MR",
    "name:und_x_variant":[
        "Ouechguech",
        "Ouechkech"
    ],
    "wof:name":"Ouechkech",
    "wof:placetype":"locality"
},
  "geometry": {"coordinates":[-12.56324,16.22767],"type":"Point"}
}