{
  "type": "Feature",
  "properties": {
    "gn:admin1_code":"10",
    "gn:asciiname":"Takoutala",
    "gn:country_code":"MR",
    "gn:dem":27,
    "gn:feature_class":"P",
    "gn:feature_code":"PPL",
    "gn:name":"Takoutala",
    "gn:population":0,
    "gn:timezone":"Africa/Nouakchott",
    "iso:country":"MR",
    "name:und_x_variant":[
        "Takoutalla",
        "Tanoutalla",
        "Takoutala"
    ],
    "wof:name":"Takoutala",
    "wof:placetype":"locality"
},
  "geometry": {"coordinates":[-12.65911,15.12562],"type":"Point"}
}