{
  "type": "Feature",
  "properties": {
    "gn:admin1_code":"02",
    "gn:asciiname":"Akenb el Abiad",
    "gn:country_code":"MR",
    "gn:dem":162,
    "gn:feature_class":"P",
    "gn:feature_code":"PPL",
    "gn:name":"Akenb el Abiad",
    "gn:population":0,
    "gn:timezone":"Africa/Nouakchott",
    "iso:country":"MR",
    "name:und_x_variant":[
        "Akemb el Abiad",
        "Akenb el Abiad"
    ],
    "wof:name":"Akenb el Abiad",
    "wof:placetype":"locality"
},
  "geometry": {"coordinates":[-9.9472,16.1571],"type":"Point"}
}