{
  "type": "Feature",
  "properties": {
    "gn:admin1_code":"00",
    "gn:asciiname":"Ndiongo",
    "gn:country_code":"MR",
    "gn:dem":10,
    "gn:feature_class":"P",
    "gn:feature_code":"PPL",
    "gn:name":"Ndiongo",
    "gn:population":0,
    "gn:timezone":"Africa/Nouakchott",
    "iso:country":"MR",
    "wof:name":"Ndiongo",
    "wof:placetype":"locality"
},
  "geometry": {"coordinates":[-15.01667,16.71667],"type":"Point"}
}