{
  "type": "Feature",
  "properties": {
    "gn:admin1_code":"00",
    "gn:asciiname":"Oujeft",
    "gn:country_code":"MR",
    "gn:dem":314,
    "gn:feature_class":"P",
    "gn:feature_code":"PPL",
    "gn:name":"Oujeft",
    "gn:population":0,
    "gn:timezone":"Africa/Nouakchott",
    "iso:country":"MR",
    "wof:lang_x_official":[
        "ara"
    ],
    "wof:lang_x_spoken":[
        "ara"
    ],
    "wof:name":"Oujeft",
    "wof:placetype":"locality"
},
  "geometry": {"coordinates":[-12.96572,20.01845],"type":"Point"}
}