{
  "type": "Feature",
  "properties": {
    "gn:admin1_code":"02",
    "gn:asciiname":"Bammeira",
    "gn:country_code":"MR",
    "gn:dem":176,
    "gn:feature_class":"P",
    "gn:feature_code":"PPL",
    "gn:name":"B\u00e2mme\u00efra",
    "gn:population":0,
    "gn:timezone":"Africa/Nouakchott",
    "iso:country":"MR",
    "wof:name":"Bammeira",
    "wof:placetype":"locality"
},
  "geometry": {"coordinates":[-9.2709,16.6642],"type":"Point"}
}