{
  "type": "Feature",
  "properties": {
    "gn:admin1_code":"04",
    "gn:asciiname":"El Harach",
    "gn:country_code":"MR",
    "gn:dem":50,
    "gn:feature_class":"P",
    "gn:feature_code":"PPL",
    "gn:name":"El Harach",
    "gn:population":0,
    "gn:timezone":"Africa/Nouakchott",
    "iso:country":"MR",
    "name:und_x_variant":[
        "Larach",
        "El Harach"
    ],
    "wof:name":"El Harach",
    "wof:placetype":"locality"
},
  "geometry": {"coordinates":[-12.44889,16.37552],"type":"Point"}
}