{
  "type": "Feature",
  "properties": {
    "gn:admin1_code":"02",
    "gn:asciiname":"Grair Anzai",
    "gn:country_code":"MR",
    "gn:dem":235,
    "gn:feature_class":"P",
    "gn:feature_code":"PPL",
    "gn:name":"Gr\u00e2\u00efr Anza\u00ef",
    "gn:population":0,
    "gn:timezone":"Africa/Nouakchott",
    "iso:country":"MR",
    "name:fra_x_preferred":[
        "Gra\u00efr Enza\u00ef"
    ],
    "name:fra_x_variant":[
        "El Gra\u00efr Enza\u00ef"
    ],
    "name:und_x_variant":[
        "Gr\u00e2\u00efr Anza\u00ef"
    ],
    "wof:lang_x_official":[
        "ara"
    ],
    "wof:lang_x_spoken":[
        "ara"
    ],
    "wof:name":"Grair Anzai",
    "wof:placetype":"locality"
},
  "geometry": {"coordinates":[-10.69017,16.73714],"type":"Point"}
}