{
  "type": "Feature",
  "properties": {
    "gn:admin1_code":"05",
    "gn:asciiname":"Vane Vane",
    "gn:country_code":"MR",
    "gn:dem":10,
    "gn:feature_class":"P",
    "gn:feature_code":"PPL",
    "gn:name":"Vane Vane",
    "gn:population":0,
    "gn:timezone":"Africa/Nouakchott",
    "iso:country":"MR",
    "name:und_x_variant":[
        "Vannvane",
        "Vane Vane"
    ],
    "wof:name":"Vane Vane",
    "wof:placetype":"locality"
},
  "geometry": {"coordinates":[-13.92791,16.31368],"type":"Point"}
}