{
  "type": "Feature",
  "properties": {
    "gn:admin1_code":"02",
    "gn:asciiname":"Bathet Dhenaba",
    "gn:country_code":"MR",
    "gn:dem":162,
    "gn:feature_class":"P",
    "gn:feature_code":"PPL",
    "gn:name":"Bathet Dhen\u00e2ba",
    "gn:population":0,
    "gn:timezone":"Africa/Nouakchott",
    "iso:country":"MR",
    "wof:name":"Bathet Dhenaba",
    "wof:placetype":"locality"
},
  "geometry": {"coordinates":[-10.908,17.1695],"type":"Point"}
}