{
  "type": "Feature",
  "properties": {
    "gn:admin1_code":"05",
    "gn:asciiname":"Diandia",
    "gn:country_code":"MR",
    "gn:dem":37,
    "gn:feature_class":"P",
    "gn:feature_code":"PPL",
    "gn:name":"Diandia",
    "gn:population":0,
    "gn:timezone":"Africa/Nouakchott",
    "iso:country":"MR",
    "name:und_x_variant":[
        "Ndian Dia",
        "Diandia"
    ],
    "wof:name":"Diandia",
    "wof:placetype":"locality"
},
  "geometry": {"coordinates":[-13.98728,16.4827],"type":"Point"}
}