{
  "type": "Feature",
  "properties": {
    "gn:admin1_code":"00",
    "gn:asciiname":"Garak",
    "gn:country_code":"MR",
    "gn:dem":7,
    "gn:feature_class":"P",
    "gn:feature_code":"PPL",
    "gn:name":"Garak",
    "gn:population":0,
    "gn:timezone":"Africa/Nouakchott",
    "iso:country":"MR",
    "name:ceb_x_preferred":[
        "Garak"
    ],
    "name:fas_x_preferred":[
        "\u06af\u0631\u06a9"
    ],
    "name:swe_x_preferred":[
        "Garak"
    ],
    "wof:name":"Garak",
    "wof:placetype":"locality"
},
  "geometry": {"coordinates":[-15.76667,16.55],"type":"Point"}
}