{
  "type": "Feature",
  "properties": {
    "gn:admin1_code":"06",
    "gn:asciiname":"Boyo",
    "gn:country_code":"MR",
    "gn:dem":4,
    "gn:feature_class":"P",
    "gn:feature_code":"PPL",
    "gn:name":"Boyo",
    "gn:population":0,
    "gn:timezone":"Africa/Nouakchott",
    "iso:country":"MR",
    "wof:name":"Boyo",
    "wof:placetype":"locality"
},
  "geometry": {"coordinates":[-16.50056,16.11108],"type":"Point"}
}