{
  "type": "Feature",
  "properties": {
    "gn:admin1_code":"06",
    "gn:asciiname":"Boyo",
    "gn:country_code":"MR",
    "gn:dem":4,
    "gn:feature_class":"P",
    "gn:feature_code":"PPL",
    "gn:name":"Boyo",
    "gn:population":0,
    "gn:timezone":"Africa/Nouakchott",
    "iso:country":"MR",
    "name:ceb_x_preferred":[
        "Boyo"
    ],
    "name:deu_x_preferred":[
        "Boyo"
    ],
    "name:fra_x_preferred":[
        "Boyo"
    ],
    "name:nld_x_preferred":[
        "Boyo"
    ],
    "name:swe_x_preferred":[
        "Boyo"
    ],
    "wof:lang_x_official":[
        "ara"
    ],
    "wof:lang_x_spoken":[
        "ara"
    ],
    "wof:name":"Boyo",
    "wof:placetype":"locality"
},
  "geometry": {"coordinates":[-16.50056,16.11108],"type":"Point"}
}