{
  "type": "Feature",
  "properties": {
    "iso:country":"MR",
    "name:ara_x_preferred":[
        "\u0648\u0627\u062f\u0627\u0646"
    ],
    "name:bel_x_preferred":[
        "\u0423\u0430\u0434\u0430\u043d"
    ],
    "name:cat_x_preferred":[
        "Ouadane"
    ],
    "name:dan_x_preferred":[
        "Ouadane"
    ],
    "name:deu_x_preferred":[
        "Ouadane"
    ],
    "name:eng_x_preferred":[
        "Ouadane"
    ],
    "name:epo_x_preferred":[
        "\u016cadano"
    ],
    "name:eus_x_preferred":[
        "Ouadane"
    ],
    "name:fin_x_preferred":[
        "Ouadane"
    ],
    "name:fra_x_preferred":[
        "Ouadane"
    ],
    "name:heb_x_preferred":[
        "\u05d5\u05d0\u05d3\u05d0\u05df"
    ],
    "name:ind_x_preferred":[
        "Ouadane"
    ],
    "name:ita_x_preferred":[
        "Ouadane"
    ],
    "name:jpn_x_preferred":[
        "\u30a6\u30a2\u30c0\u30f3"
    ],
    "name:kab_x_preferred":[
        "Wadan"
    ],
    "name:kat_x_preferred":[
        "\u10e3\u10d0\u10d3\u10d0\u10dc\u10d8"
    ],
    "name:lit_x_preferred":[
        "Uadanas"
    ],
    "name:msa_x_preferred":[
        "Ouadane"
    ],
    "name:nep_x_preferred":[
        "\u0913\u0926\u0947\u0928"
    ],
    "name:nld_x_preferred":[
        "Ouadane"
    ],
    "name:nob_x_preferred":[
        "Ouadane"
    ],
    "name:nor_x_preferred":[
        "Ouadane"
    ],
    "name:pol_x_preferred":[
        "Wadan"
    ],
    "name:por_x_preferred":[
        "Ouadane"
    ],
    "name:ron_x_preferred":[
        "Ouadane"
    ],
    "name:rus_x_preferred":[
        "\u0423\u0430\u0434\u0430\u043d"
    ],
    "name:spa_x_preferred":[
        "Ouadane"
    ],
    "name:swe_x_preferred":[
        "Ouadane"
    ],
    "name:tur_x_preferred":[
        "Ouadane"
    ],
    "name:ukr_x_preferred":[
        "\u0423\u0430\u0434\u0430\u043d"
    ],
    "name:und_x_variant":[
        "Oudane"
    ],
    "name:urd_x_preferred":[
        "\u0648\u0627\u062f\u0627\u0646"
    ],
    "name:zho_x_preferred":[
        "\u74e6\u4e39"
    ],
    "qs:gn_country":"MR",
    "qs:gn_fcode":"PPL",
    "qs:gn_pop":0,
    "qs:name":"Ouadane",
    "qs:name_adm0":"Mauritanie",
    "qs:name_adm1":"Adrar",
    "qs:photos":66,
    "qs:photos_1k":13,
    "qs:photos_9k":1,
    "qs:photos_9r":2,
    "qs:photos_all":66,
    "qs:photos_sr":2,
    "qs:placetype":"Town",
    "qs:pop_sr":"4",
    "qs:woe_adm0":23424896,
    "wd:wordcount":1393,
    "wof:lang_x_official":[
        "ara"
    ],
    "wof:lang_x_spoken":[
        "ara"
    ],
    "wof:name":"Ouadane",
    "wof:placetype":"locality"
},
  "geometry": {"coordinates":[-11.62138,20.92767],"type":"Point"}
}