{
  "type": "Feature",
  "properties": {
    "gn:admin1_code":"07",
    "gn:asciiname":"Mhaireth",
    "gn:country_code":"MR",
    "gn:dem":371,
    "gn:feature_class":"P",
    "gn:feature_code":"PPL",
    "gn:name":"M\u1e25a\u00efreth",
    "gn:population":0,
    "gn:timezone":"Africa/Nouakchott",
    "iso:country":"MR",
    "wof:name":"Mhaireth",
    "wof:placetype":"locality"
},
  "geometry": {"coordinates":[-13.00388,20.27824],"type":"Point"}
}