{
  "type": "Feature",
  "properties": {
    "gn:admin1_code":"01",
    "gn:asciiname":"Taghaoumit",
    "gn:country_code":"MR",
    "gn:dem":223,
    "gn:feature_class":"P",
    "gn:feature_code":"PPL",
    "gn:name":"Taghaoum\u00eet",
    "gn:population":0,
    "gn:timezone":"Africa/Nouakchott",
    "iso:country":"MR",
    "wof:name":"Taghaoumit",
    "wof:placetype":"locality"
},
  "geometry": {"coordinates":[-7.3584,16.9417],"type":"Point"}
}