{
  "type": "Feature",
  "properties": {
    "gn:admin1_code":"05",
    "gn:asciiname":"Olo Ologo",
    "gn:country_code":"MR",
    "gn:dem":7,
    "gn:feature_class":"P",
    "gn:feature_code":"PPL",
    "gn:name":"Olo Ologo",
    "gn:population":0,
    "gn:timezone":"Africa/Nouakchott",
    "iso:country":"MR",
    "wof:name":"Olo Ologo",
    "wof:placetype":"locality"
},
  "geometry": {"coordinates":[-14.5442,16.6426],"type":"Point"}
}