{
  "type": "Feature",
  "properties": {
    "gn:admin1_code":"01",
    "gn:asciiname":"Hassei ech Cha`ba",
    "gn:country_code":"MR",
    "gn:dem":269,
    "gn:feature_class":"P",
    "gn:feature_code":"PPL",
    "gn:name":"H\u00e2sse\u00ef ech Cha\u2018ba",
    "gn:population":0,
    "gn:timezone":"Africa/Nouakchott",
    "iso:country":"MR",
    "wof:name":"Hassei ech Cha`ba",
    "wof:placetype":"locality"
},
  "geometry": {"coordinates":[-7.14529,16.2826],"type":"Point"}
}