{
  "type": "Feature",
  "properties": {
    "gn:admin1_code":"04",
    "gn:asciiname":"Mouenite",
    "gn:country_code":"MR",
    "gn:dem":51,
    "gn:feature_class":"P",
    "gn:feature_code":"PPL",
    "gn:name":"Mou\u00e9nit\u00e9",
    "gn:population":0,
    "gn:timezone":"Africa/Nouakchott",
    "iso:country":"MR",
    "wof:name":"Mouenite",
    "wof:placetype":"locality"
},
  "geometry": {"coordinates":[-12.56835,15.77219],"type":"Point"}
}