{
  "type": "Feature",
  "properties": {
    "gn:admin1_code":"01",
    "gn:asciiname":"El Mseggme",
    "gn:country_code":"MR",
    "gn:dem":251,
    "gn:feature_class":"P",
    "gn:feature_code":"PPL",
    "gn:name":"El Mseggm\u00e9",
    "gn:population":0,
    "gn:timezone":"Africa/Nouakchott",
    "iso:country":"MR",
    "name:und_x_variant":[
        "El Msegm\u00e9",
        "El Mseggm\u00e9"
    ],
    "wof:name":"El Mseggme",
    "wof:placetype":"locality"
},
  "geometry": {"coordinates":[-7.1973,16.3189],"type":"Point"}
}