{
  "type": "Feature",
  "properties": {
    "gn:admin1_code":"05",
    "gn:asciiname":"Ngorel",
    "gn:country_code":"MR",
    "gn:dem":10,
    "gn:feature_class":"P",
    "gn:feature_code":"PPL",
    "gn:name":"Ngorel",
    "gn:population":0,
    "gn:timezone":"Africa/Nouakchott",
    "iso:country":"MR",
    "name:und_x_variant":[
        "N\u2019Gora\u00ef",
        "Ngorel"
    ],
    "wof:name":"Ngorel",
    "wof:placetype":"locality"
},
  "geometry": {"coordinates":[-14.34492,16.63864],"type":"Point"}
}