{
  "type": "Feature",
  "properties": {
    "gn:admin1_code":"02",
    "gn:asciiname":"Bargatanni",
    "gn:country_code":"MR",
    "gn:dem":237,
    "gn:feature_class":"P",
    "gn:feature_code":"PPL",
    "gn:name":"Bargatanni",
    "gn:population":0,
    "gn:timezone":"Africa/Nouakchott",
    "iso:country":"MR",
    "name:fra_x_preferred":[
        "Bargatanni"
    ],
    "name:fra_x_variant":[
        "Bergatanni"
    ],
    "name:und_x_variant":[
        "Bergatanni"
    ],
    "wof:name":"Bargatanni",
    "wof:placetype":"locality"
},
  "geometry": {"coordinates":[-10.7535,16.8196],"type":"Point"}
}