{
  "type": "Feature",
  "properties": {
    "gn:admin1_code":"10",
    "gn:asciiname":"Yeni",
    "gn:country_code":"MR",
    "gn:dem":61,
    "gn:feature_class":"P",
    "gn:feature_code":"PPL",
    "gn:name":"Y\u00e9ni",
    "gn:population":0,
    "gn:timezone":"Africa/Nouakchott",
    "iso:country":"MR",
    "wof:name":"Yeni",
    "wof:placetype":"locality"
},
  "geometry": {"coordinates":[-12.36932,15.8021],"type":"Point"}
}