{
  "type": "Feature",
  "properties": {
    "gn:admin1_code":"10",
    "gn:asciiname":"Zenegue Maures",
    "gn:country_code":"MR",
    "gn:dem":51,
    "gn:feature_class":"P",
    "gn:feature_code":"PPL",
    "gn:name":"Z\u00e9n\u00e9gu\u00e9 Maures",
    "gn:population":0,
    "gn:timezone":"Africa/Nouakchott",
    "iso:country":"MR",
    "name:und_x_variant":[
        "Z\u00e9n\u00e9gu\u00e9 Maure",
        "Z\u00e9n\u00e9gu\u00e9 Maures"
    ],
    "wof:lang_x_official":[
        "ara"
    ],
    "wof:lang_x_spoken":[
        "ara"
    ],
    "wof:name":"Zenegue Maures",
    "wof:placetype":"locality"
},
  "geometry": {"coordinates":[-12.2722,15.11172],"type":"Point"}
}