{
  "type": "Feature",
  "properties": {
    "gn:admin1_code":"09",
    "gn:asciiname":"Nimlane",
    "gn:country_code":"MR",
    "gn:dem":407,
    "gn:feature_class":"P",
    "gn:feature_code":"PPL",
    "gn:name":"Nimlane",
    "gn:population":0,
    "gn:timezone":"Africa/Nouakchott",
    "iso:country":"MR",
    "wof:name":"Nimlane",
    "wof:placetype":"locality"
},
  "geometry": {"coordinates":[-11.59676,18.39819],"type":"Point"}
}