{
  "type": "Feature",
  "properties": {
    "gn:admin1_code":"05",
    "gn:asciiname":"Haimedat",
    "gn:country_code":"MR",
    "gn:dem":8,
    "gn:feature_class":"P",
    "gn:feature_code":"PPL",
    "gn:name":"Ha\u00efm\u00e9d\u00e2t",
    "gn:population":0,
    "gn:timezone":"Africa/Nouakchott",
    "iso:country":"MR",
    "wof:lang_x_official":[
        "ara"
    ],
    "wof:lang_x_spoken":[
        "ara"
    ],
    "wof:name":"Haimedat",
    "wof:placetype":"locality"
},
  "geometry": {"coordinates":[-13.80025,16.17983],"type":"Point"}
}