{
  "type": "Feature",
  "properties": {
    "gn:admin1_code":"01",
    "gn:asciiname":"'Ain Bire",
    "gn:country_code":"MR",
    "gn:dem":213,
    "gn:feature_class":"P",
    "gn:feature_code":"PPL",
    "gn:name":"\u2019A\u00efn B\u00eer\u00e9",
    "gn:population":0,
    "gn:timezone":"Africa/Nouakchott",
    "iso:country":"MR",
    "wof:name":"'Ain Bire",
    "wof:placetype":"locality"
},
  "geometry": {"coordinates":[-8.0988,16.1446],"type":"Point"}
}