{
  "type": "Feature",
  "properties": {
    "gn:admin1_code":"07",
    "gn:asciiname":"Hamdoun",
    "gn:country_code":"MR",
    "gn:dem":198,
    "gn:feature_class":"P",
    "gn:feature_code":"PPL",
    "gn:name":"\u1e24amdo\u00fbn",
    "gn:population":0,
    "gn:timezone":"Africa/Nouakchott",
    "iso:country":"MR",
    "wof:name":"Hamdoun",
    "wof:placetype":"locality"
},
  "geometry": {"coordinates":[-13.14509,20.32027],"type":"Point"}
}