{
  "type": "Feature",
  "properties": {
    "gn:admin1_code":"03",
    "gn:asciiname":"Oumm Kchera",
    "gn:country_code":"MR",
    "gn:dem":292,
    "gn:feature_class":"P",
    "gn:feature_code":"PPL",
    "gn:name":"Oumm Kch\u00e9ra",
    "gn:population":0,
    "gn:timezone":"Africa/Nouakchott",
    "iso:country":"MR",
    "name:und_x_variant":[
        "Oumkch\u00e9ra",
        "Oumm Kch\u00e9ra"
    ],
    "wof:name":"Oumm Kchera",
    "wof:placetype":"locality"
},
  "geometry": {"coordinates":[-11.12864,15.63549],"type":"Point"}
}