{
  "type": "Feature",
  "properties": {
    "gn:admin1_code":"00",
    "gn:asciiname":"Lahouvich",
    "gn:country_code":"MR",
    "gn:dem":21,
    "gn:feature_class":"P",
    "gn:feature_code":"PPL",
    "gn:name":"Lahouvich",
    "gn:population":0,
    "gn:timezone":"Africa/Nouakchott",
    "iso:country":"MR",
    "wof:name":"Lahouvich",
    "wof:placetype":"locality"
},
  "geometry": {"coordinates":[-15.98333,16.63332999999999],"type":"Point"}
}