{
  "type": "Feature",
  "properties": {
    "gn:admin1_code":"05",
    "gn:asciiname":"Diammel Vidim",
    "gn:country_code":"MR",
    "gn:dem":12,
    "gn:feature_class":"P",
    "gn:feature_code":"PPL",
    "gn:name":"Diammel Vidim",
    "gn:population":0,
    "gn:timezone":"Africa/Nouakchott",
    "iso:country":"MR",
    "name:und_x_variant":[
        "Diamel Vidim",
        "Diammel Vidim"
    ],
    "wof:name":"Diammel Vidim",
    "wof:placetype":"locality"
},
  "geometry": {"coordinates":[-13.94957,16.26439],"type":"Point"}
}