{
  "type": "Feature",
  "properties": {
    "gn:admin1_code":"03",
    "gn:asciiname":"El Maleh",
    "gn:country_code":"MR",
    "gn:dem":160,
    "gn:feature_class":"P",
    "gn:feature_code":"PPL",
    "gn:name":"El Maleh",
    "gn:population":0,
    "gn:timezone":"Africa/Nouakchott",
    "iso:country":"MR",
    "name:und_x_variant":[
        "El Mali",
        "El Maleh"
    ],
    "wof:name":"El Maleh",
    "wof:placetype":"locality"
},
  "geometry": {"coordinates":[-11.29156,15.53306],"type":"Point"}
}