{
  "type": "Feature",
  "properties": {
    "gn:admin1_code":"04",
    "gn:asciiname":"Ouedamor Gobingoa",
    "gn:country_code":"MR",
    "gn:dem":71,
    "gn:feature_class":"P",
    "gn:feature_code":"PPL",
    "gn:name":"Ou\u00e9damor Gobingoa",
    "gn:population":0,
    "gn:timezone":"Africa/Nouakchott",
    "iso:country":"MR",
    "wof:lang_x_official":[
        "ara"
    ],
    "wof:lang_x_spoken":[
        "ara"
    ],
    "wof:name":"Ouedamor Gobingoa",
    "wof:placetype":"locality"
},
  "geometry": {"coordinates":[-12.66902,15.81817],"type":"Point"}
}