{
  "type": "Feature",
  "properties": {
    "gn:admin1_code":"04",
    "gn:asciiname":"Guiraye",
    "gn:country_code":"MR",
    "gn:dem":11,
    "gn:feature_class":"P",
    "gn:feature_code":"PPL",
    "gn:name":"Guiraye",
    "gn:population":0,
    "gn:timezone":"Africa/Nouakchott",
    "iso:country":"MR",
    "name:und_x_variant":[
        "Goureye",
        "Guireye",
        "Guira\u00ef",
        "Guiraye"
    ],
    "wof:name":"Guiraye",
    "wof:placetype":"locality"
},
  "geometry": {"coordinates":[-13.45449,16.1019],"type":"Point"}
}