{
  "type": "Feature",
  "properties": {
    "gn:admin1_code":"03",
    "gn:asciiname":"El `Erg",
    "gn:country_code":"MR",
    "gn:dem":247,
    "gn:feature_class":"P",
    "gn:feature_code":"PPL",
    "gn:name":"El \u2018Erg",
    "gn:population":0,
    "gn:timezone":"Africa/Nouakchott",
    "iso:country":"MR",
    "name:und_x_variant":[
        "Leherik",
        "El \u2018Erg"
    ],
    "wof:name":"El `Erg",
    "wof:placetype":"locality"
},
  "geometry": {"coordinates":[-11.10435,15.69867],"type":"Point"}
}