{
  "type": "Feature",
  "properties": {
    "gn:admin1_code":"01",
    "gn:asciiname":"El Ghar",
    "gn:country_code":"MR",
    "gn:dem":283,
    "gn:feature_class":"P",
    "gn:feature_code":"PPL",
    "gn:name":"El Gh\u00e2r",
    "gn:population":0,
    "gn:timezone":"Africa/Nouakchott",
    "iso:country":"MR",
    "wof:name":"El Ghar",
    "wof:placetype":"locality"
},
  "geometry": {"coordinates":[-7.1242,16.3505],"type":"Point"}
}