{
  "type": "Feature",
  "properties": {
    "gn:admin1_code":"10",
    "gn:asciiname":"Ahel el Jeilani",
    "gn:country_code":"MR",
    "gn:dem":122,
    "gn:feature_class":"P",
    "gn:feature_code":"PPL",
    "gn:name":"Ahel el Je\u00eflani",
    "gn:population":0,
    "gn:timezone":"Africa/Nouakchott",
    "iso:country":"MR",
    "wof:name":"Ahel el Jeilani",
    "wof:placetype":"locality"
},
  "geometry": {"coordinates":[-11.74359,15.98644],"type":"Point"}
}