{
  "type": "Feature",
  "properties": {
    "gn:admin1_code":"10",
    "gn:asciiname":"Gourel Bamol",
    "gn:country_code":"MR",
    "gn:dem":42,
    "gn:feature_class":"P",
    "gn:feature_code":"PPL",
    "gn:name":"Gourel Bamol",
    "gn:population":0,
    "gn:timezone":"Africa/Nouakchott",
    "iso:country":"MR",
    "wof:name":"Gourel Bamol",
    "wof:placetype":"locality"
},
  "geometry": {"coordinates":[-12.42941,15.49005],"type":"Point"}
}