{
  "type": "Feature",
  "properties": {
    "gn:admin1_code":"01",
    "gn:asciiname":"Egemanbenou",
    "gn:country_code":"MR",
    "gn:dem":237,
    "gn:feature_class":"P",
    "gn:feature_code":"PPL",
    "gn:name":"Eg\u00e9manb\u00e9nou",
    "gn:population":0,
    "gn:timezone":"Africa/Nouakchott",
    "iso:country":"MR",
    "name:und_x_variant":[
        "Egu\u00e9manb\u00e9nou",
        "Eg\u00e9manb\u00e9nou"
    ],
    "wof:lang_x_official":[
        "ara"
    ],
    "wof:lang_x_spoken":[
        "ara"
    ],
    "wof:name":"Egemanbenou",
    "wof:placetype":"locality"
},
  "geometry": {"coordinates":[-8.6615,15.84446],"type":"Point"}
}