{
  "type": "Feature",
  "properties": {
    "gn:admin1_code":"NKC",
    "gn:asciiname":"Jreida",
    "gn:country_code":"MR",
    "gn:dem":3,
    "gn:feature_class":"P",
    "gn:feature_code":"PPL",
    "gn:name":"Jre\u00efda",
    "gn:population":0,
    "gn:timezone":"Africa/Nouakchott",
    "iso:country":"MR",
    "name:fra_x_preferred":[
        "Jre\u00efda"
    ],
    "name:fra_x_variant":[
        "Djereida",
        "Coppolani"
    ],
    "name:und_x_variant":[
        "Coppolani",
        "Djereida"
    ],
    "wof:name":"Jreida",
    "wof:placetype":"locality"
},
  "geometry": {"coordinates":[-16.0401,18.31846],"type":"Point"}
}