{
  "type": "Feature",
  "properties": {
    "gn:admin1_code":"01",
    "gn:asciiname":"En Njama",
    "gn:country_code":"MR",
    "gn:dem":270,
    "gn:feature_class":"P",
    "gn:feature_code":"PPL",
    "gn:name":"En Nj\u00e2ma",
    "gn:population":0,
    "gn:timezone":"Africa/Nouakchott",
    "iso:country":"MR",
    "wof:name":"En Njama",
    "wof:placetype":"locality"
},
  "geometry": {"coordinates":[-7.247,16.0308],"type":"Point"}
}