{
  "type": "Feature",
  "properties": {
    "gn:admin1_code":"02",
    "gn:asciiname":"Aioun",
    "gn:country_code":"MR",
    "gn:dem":235,
    "gn:feature_class":"P",
    "gn:feature_code":"PPLA",
    "gn:name":"Aioun",
    "gn:population":12635,
    "gn:timezone":"Africa/Nouakchott",
    "iso:country":"MR",
    "name:ara_x_preferred":[
        "\u0644\u0639\u064a\u0648\u0646"
    ],
    "name:ara_x_variant":[
        "\u0627\u0644\u0639\u064a\u0648\u0646",
        "\u0639\u064a\u0648\u0646 \u0627\u0644\u0639\u062a\u0631\u0648\u0633"
    ],
    "name:bel_x_preferred":[
        "\u0410\u044e\u043d-\u044d\u043b\u044c-\u0410\u0442\u0440\u0443\u0441"
    ],
    "name:ceb_x_preferred":[
        "Aioun"
    ],
    "name:deu_x_preferred":[
        "Ayo\u00fbn el-Atro\u00fbs"
    ],
    "name:eng_x_preferred":[
        "Ayoun El Atrous"
    ],
    "name:epo_x_preferred":[
        "Ajun-el-Atrus"
    ],
    "name:eus_x_preferred":[
        "Aiun el-Atrus"
    ],
    "name:ita_x_preferred":[
        "Ayoun el-Atrouss"
    ],
    "name:kor_x_preferred":[
        "\uc544\uc724\uc5d8\uc544\ud2b8\ub8e8\uc2a4"
    ],
    "name:nor_x_preferred":[
        "Ayoun El Atrous"
    ],
    "name:pol_x_preferred":[
        "Ujun al-Atrus"
    ],
    "name:ron_x_preferred":[
        "Ayo\u00fbn el-Atro\u00fbs"
    ],
    "name:rus_x_preferred":[
        "\u0410\u044e\u043d-\u044d\u043b\u044c-\u0410\u0442\u0440\u0443\u0441"
    ],
    "name:ukr_x_preferred":[
        "\u0410\u044e\u043d-\u0435\u043b\u044c-\u0410\u0442\u0440\u0443\u0441"
    ],
    "name:und_x_variant":[
        "A\u00efoun el Atrouss",
        "\u2019Ayo\u00fbn el \u2019Atro\u00fbs",
        "Aioun",
        "A\u00efoun",
        "Ayo\u00fbn el Atro\u00fbs",
        "La\u2018y\u016bn",
        "Al \u2018Ay\u016bn",
        "\u2018Uy\u016bn al \u2018Atr\u016bs",
        "\u2018Ay\u016bn al \u2018Atr\u016bs",
        "Lu\u2018y\u016bn",
        "Al \u2018Uy\u016bn"
    ],
    "name:urd_x_preferred":[
        "\u0639\u06cc\u0648\u0646 \u0627\u0644\u0639\u062a\u0631\u0648\u0633"
    ],
    "name:zho_x_preferred":[
        "\u963f\u5c24\u6069\u963f\u7279\u9b6f\u65af"
    ],
    "wof:name":"Aioun",
    "wof:placetype":"locality",
    "wof:population":12635
},
  "geometry": {"coordinates":[-9.6149,16.6614],"type":"Point"}
}