{
  "type": "Feature",
  "properties": {
    "gn:admin1_code":"06",
    "gn:asciiname":"Tekane",
    "gn:cc2":"MR",
    "gn:country_code":"MR",
    "gn:dem":6,
    "gn:feature_class":"P",
    "gn:feature_code":"PPL",
    "gn:name":"T\u00e9kane",
    "gn:population":22041,
    "gn:timezone":"Africa/Nouakchott",
    "iso:country":"MR",
    "name:und_x_variant":[
        "Ti\u00e9kane",
        "T\u00e9kane"
    ],
    "wof:name":"Tekane",
    "wof:placetype":"locality",
    "wof:population":22041
},
  "geometry": {"coordinates":[-15.45972,16.57806],"type":"Point"}
}