{
  "type": "Feature",
  "properties": {
    "gn:admin1_code":"01",
    "gn:asciiname":"Tchera Oulad El Faghi",
    "gn:country_code":"MR",
    "gn:dem":292,
    "gn:feature_class":"P",
    "gn:feature_code":"PPL",
    "gn:name":"Tch\u00e9ra Oulad El Faghi",
    "gn:population":0,
    "gn:timezone":"Africa/Nouakchott",
    "iso:country":"MR",
    "name:und_x_variant":[
        "Tch\u00e9ra Oulad el Fagui",
        "Tch\u00e9ra Oulad El Faghi"
    ],
    "wof:lang_x_official":[
        "ara"
    ],
    "wof:lang_x_spoken":[
        "ara"
    ],
    "wof:name":"Tchera Oulad El Faghi",
    "wof:placetype":"locality"
},
  "geometry": {"coordinates":[-7.75566,15.62923],"type":"Point"}
}