{
  "type": "Feature",
  "properties": {
    "gn:admin1_code":"03",
    "gn:asciiname":"Ibachelene",
    "gn:country_code":"MR",
    "gn:dem":227,
    "gn:feature_class":"P",
    "gn:feature_code":"PPL",
    "gn:name":"Ibachel\u00e9ne",
    "gn:population":0,
    "gn:timezone":"Africa/Nouakchott",
    "iso:country":"MR",
    "wof:name":"Ibachelene",
    "wof:placetype":"locality"
},
  "geometry": {"coordinates":[-11.08882,15.85191],"type":"Point"}
}