{
  "type": "Feature",
  "properties": {
    "gn:admin1_code":"03",
    "gn:asciiname":"Modi Founti",
    "gn:country_code":"MR",
    "gn:dem":53,
    "gn:feature_class":"P",
    "gn:feature_code":"PPL",
    "gn:name":"M\u00f4di Fo\u00fbnti",
    "gn:population":0,
    "gn:timezone":"Africa/Nouakchott",
    "iso:country":"MR",
    "wof:name":"Modi Founti",
    "wof:placetype":"locality"
},
  "geometry": {"coordinates":[-12.82957,16.83407],"type":"Point"}
}