{
  "type": "Feature",
  "properties": {
    "gn:admin1_code":"10",
    "gn:asciiname":"Baediam",
    "gn:country_code":"MR",
    "gn:dem":55,
    "gn:feature_class":"P",
    "gn:feature_code":"PPL",
    "gn:name":"Ba\u00e9diam",
    "gn:population":0,
    "gn:timezone":"Africa/Nouakchott",
    "iso:country":"MR",
    "name:und_x_variant":[
        "Boediam",
        "Ba\u00e9diam\u00e9",
        "Ba\u00e9diam"
    ],
    "wof:name":"Baediam",
    "wof:placetype":"locality"
},
  "geometry": {"coordinates":[-11.85106,15.05655],"type":"Point"}
}