{
  "type": "Feature",
  "properties": {
    "gn:admin1_code":"10",
    "gn:asciiname":"Hamdallaye",
    "gn:country_code":"MR",
    "gn:dem":88,
    "gn:feature_class":"P",
    "gn:feature_code":"PPL",
    "gn:name":"Hamdallaye",
    "gn:population":0,
    "gn:timezone":"Africa/Nouakchott",
    "iso:country":"MR",
    "name:deu_x_preferred":[
        "Hamdallaye"
    ],
    "name:fra_x_preferred":[
        "Hamdallaye"
    ],
    "wof:name":"Hamdallaye",
    "wof:placetype":"locality"
},
  "geometry": {"coordinates":[-12.10253,15.23275],"type":"Point"}
}