{
  "type": "Feature",
  "properties": {
    "gn:admin1_code":"03",
    "gn:asciiname":"Djib",
    "gn:country_code":"MR",
    "gn:dem":52,
    "gn:feature_class":"P",
    "gn:feature_code":"PPL",
    "gn:name":"Djib",
    "gn:population":0,
    "gn:timezone":"Africa/Nouakchott",
    "iso:country":"MR",
    "wof:name":"Djib",
    "wof:placetype":"locality"
},
  "geometry": {"coordinates":[-12.67383,16.55542],"type":"Point"}
}