{
  "type": "Feature",
  "properties": {
    "gn:admin1_code":"01",
    "gn:asciiname":"'Adel Bagrou",
    "gn:country_code":"MR",
    "gn:dem":255,
    "gn:feature_class":"P",
    "gn:feature_code":"PPL",
    "gn:name":"\u2019Adel Bagrou",
    "gn:population":0,
    "gn:timezone":"Africa/Nouakchott",
    "iso:country":"MR",
    "name:pol_x_preferred":[
        "Adl Bakru"
    ],
    "name:und_x_variant":[
        "Abdel Begrou",
        "\u2019Adel Bagrou"
    ],
    "name:zho_x_preferred":[
        "\u963f\u4ee3\u52d2\u5df4\u683c\u9b6f"
    ],
    "wof:name":"'Adel Bagrou",
    "wof:placetype":"locality"
},
  "geometry": {"coordinates":[-6.95056,15.4975],"type":"Point"}
}