{
  "type": "Feature",
  "properties": {
    "gn:admin1_code":"01",
    "gn:asciiname":"'Adel Bagrou",
    "gn:country_code":"MR",
    "gn:dem":255,
    "gn:feature_class":"P",
    "gn:feature_code":"PPL",
    "gn:name":"\u2019Adel Bagrou",
    "gn:population":0,
    "gn:timezone":"Africa/Nouakchott",
    "iso:country":"MR",
    "name:ara_x_preferred":[
        "\u0639\u062f\u0644 \u0628\u0643\u0631\u0648"
    ],
    "name:azb_x_preferred":[
        "\u0627\u062f\u0644 \u0628\u0627\u0642\u0631\u0648"
    ],
    "name:dan_x_preferred":[
        "Adel Bagrou"
    ],
    "name:deu_x_preferred":[
        "Adel Bagrou"
    ],
    "name:fas_x_preferred":[
        "\u0627\u062f\u0644 \u0628\u0627\u06af\u0631\u0648"
    ],
    "name:fra_x_preferred":[
        "Adel Bagrou"
    ],
    "name:ita_x_preferred":[
        "Adel Bagrou"
    ],
    "name:msa_x_preferred":[
        "Adel Bagrou"
    ],
    "name:pol_x_preferred":[
        "Adl Bakru"
    ],
    "name:ron_x_preferred":[
        "Adel Bagrou"
    ],
    "name:rus_x_preferred":[
        "\u0410\u0434\u0435\u043b\u044c-\u0411\u0430\u0433\u0440\u0443"
    ],
    "name:spa_x_preferred":[
        "Adel Bagrou"
    ],
    "name:swe_x_preferred":[
        "Adel Bagrou"
    ],
    "name:und_x_variant":[
        "Abdel Begrou",
        "\u2019Adel Bagrou"
    ],
    "name:zho_x_preferred":[
        "\u963f\u4ee3\u52d2\u5df4\u683c\u9b6f"
    ],
    "wof:name":"'Adel Bagrou",
    "wof:placetype":"locality"
},
  "geometry": {"coordinates":[-6.95056,15.4975],"type":"Point"}
}