{
  "type": "Feature",
  "properties": {
    "gn:admin1_code":"04",
    "gn:asciiname":"Ouro Ndom",
    "gn:country_code":"MR",
    "gn:dem":42,
    "gn:feature_class":"P",
    "gn:feature_code":"PPL",
    "gn:name":"Ouro Ndom",
    "gn:population":0,
    "gn:timezone":"Africa/Nouakchott",
    "iso:country":"MR",
    "wof:name":"Ouro Ndom",
    "wof:placetype":"locality"
},
  "geometry": {"coordinates":[-12.66494,15.55051],"type":"Point"}
}