{
  "type": "Feature",
  "properties": {
    "gn:admin1_code":"07",
    "gn:asciiname":"Tachot",
    "gn:country_code":"MR",
    "gn:dem":192,
    "gn:feature_class":"P",
    "gn:feature_code":"PPL",
    "gn:name":"T\u00e2ch\u00f4t",
    "gn:population":0,
    "gn:timezone":"Africa/Nouakchott",
    "iso:country":"MR",
    "wof:name":"Tachot",
    "wof:placetype":"locality"
},
  "geometry": {"coordinates":[-13.11301,20.3939],"type":"Point"}
}