{
  "type": "Feature",
  "properties": {
    "gn:admin1_code":"06",
    "gn:asciiname":"Mbalal",
    "gn:country_code":"MR",
    "gn:dem":12,
    "gn:feature_class":"P",
    "gn:feature_code":"PPL",
    "gn:name":"Mbalal",
    "gn:population":0,
    "gn:timezone":"Africa/Nouakchott",
    "iso:country":"MR",
    "name:ara_x_preferred":[
        "\u0627\u0645\u0628\u0644\u0644"
    ],
    "name:fra_x_preferred":[
        "M'Balel"
    ],
    "name:ita_x_preferred":[
        "M'Balel"
    ],
    "name:msa_x_preferred":[
        "Mbalal"
    ],
    "name:ron_x_preferred":[
        "M'Balel"
    ],
    "name:spa_x_preferred":[
        "M'Balel"
    ],
    "wof:lang_x_official":[
        "ara"
    ],
    "wof:lang_x_spoken":[
        "ara"
    ],
    "wof:name":"Mbalal",
    "wof:placetype":"locality"
},
  "geometry": {"coordinates":[-16.01,16.655],"type":"Point"}
}