{
  "type": "Feature",
  "properties": {
    "gn:admin1_code":"05",
    "gn:asciiname":"Haire Mbar",
    "gn:country_code":"MR",
    "gn:dem":12,
    "gn:feature_class":"P",
    "gn:feature_code":"PPL",
    "gn:name":"Ha\u00efre Mbar",
    "gn:population":0,
    "gn:timezone":"Africa/Nouakchott",
    "iso:country":"MR",
    "name:swe_x_preferred":[
        "A\u00e9r\u00e9 M'Bar"
    ],
    "name:und_x_variant":[
        "A\u00e9r\u00e9 Mbar",
        "Ha\u00e9r\u00e9 Mbar",
        "Ha\u00efre Mbar"
    ],
    "wof:name":"Haire Mbar",
    "wof:placetype":"locality"
},
  "geometry": {"coordinates":[-14.05658,16.40684],"type":"Point"}
}