{
  "type": "Feature",
  "properties": {
    "gn:admin1_code":"10",
    "gn:asciiname":"Govin Kare",
    "gn:country_code":"MR",
    "gn:dem":33,
    "gn:feature_class":"P",
    "gn:feature_code":"PPL",
    "gn:name":"Govin Kar\u00e9",
    "gn:population":0,
    "gn:timezone":"Africa/Nouakchott",
    "iso:country":"MR",
    "name:und_x_variant":[
        "Goven Kar\u00e9",
        "Govin Kar\u00e9"
    ],
    "wof:name":"Govin Kare",
    "wof:placetype":"locality"
},
  "geometry": {"coordinates":[-12.62587,15.26127],"type":"Point"}
}