{
  "type": "Feature",
  "properties": {
    "gn:admin1_code":"10",
    "gn:asciiname":"Ouiouat",
    "gn:country_code":"MR",
    "gn:dem":82,
    "gn:feature_class":"P",
    "gn:feature_code":"PPL",
    "gn:name":"Ouiouat",
    "gn:population":0,
    "gn:timezone":"Africa/Nouakchott",
    "iso:country":"MR",
    "name:und_x_variant":[
        "Wiwatt",
        "Ouiouat"
    ],
    "wof:lang_x_official":[
        "ara"
    ],
    "wof:lang_x_spoken":[
        "ara"
    ],
    "wof:name":"Ouiouat",
    "wof:placetype":"locality"
},
  "geometry": {"coordinates":[-11.93973,15.23362],"type":"Point"}
}