{
  "type": "Feature",
  "properties": {
    "gn:admin1_code":"05",
    "gn:asciiname":"Louad Touil",
    "gn:country_code":"MR",
    "gn:dem":13,
    "gn:feature_class":"P",
    "gn:feature_code":"PPL",
    "gn:name":"Louad Touil",
    "gn:population":0,
    "gn:timezone":"Africa/Nouakchott",
    "iso:country":"MR",
    "name:und_x_variant":[
        "Lougu\u00e9 Poti\u00e9",
        "Louad Touil"
    ],
    "wof:name":"Louad Touil",
    "wof:placetype":"locality"
},
  "geometry": {"coordinates":[-14.46331,16.79077],"type":"Point"}
}