{
  "type": "Feature",
  "properties": {
    "gn:admin1_code":"03",
    "gn:asciiname":"Oumoulbarka",
    "gn:country_code":"MR",
    "gn:dem":175,
    "gn:feature_class":"P",
    "gn:feature_code":"PPL",
    "gn:name":"Oumoulbarka",
    "gn:population":0,
    "gn:timezone":"Africa/Nouakchott",
    "iso:country":"MR",
    "name:und_x_variant":[
        "Oumm el Barka",
        "Oumoulbarka"
    ],
    "wof:name":"Oumoulbarka",
    "wof:placetype":"locality"
},
  "geometry": {"coordinates":[-10.84663,15.58929],"type":"Point"}
}