{
  "type": "Feature",
  "properties": {
    "gn:admin1_code":"10",
    "gn:asciiname":"Sei Deleme",
    "gn:country_code":"MR",
    "gn:dem":66,
    "gn:feature_class":"P",
    "gn:feature_code":"PPL",
    "gn:name":"Se\u00ef D\u00e9l\u00e9m\u00e9",
    "gn:population":0,
    "gn:timezone":"Africa/Nouakchott",
    "iso:country":"MR",
    "name:und_x_variant":[
        "Hassi Delme",
        "Se\u00ef D\u00e9l\u00e9m\u00e9"
    ],
    "wof:name":"Sei Deleme",
    "wof:placetype":"locality"
},
  "geometry": {"coordinates":[-11.95446,15.12895],"type":"Point"}
}