{
  "type": "Feature",
  "properties": {
    "gn:admin1_code":"03",
    "gn:asciiname":"Dernie",
    "gn:country_code":"MR",
    "gn:dem":183,
    "gn:feature_class":"P",
    "gn:feature_code":"PPL",
    "gn:name":"Derni\u00e9",
    "gn:population":0,
    "gn:timezone":"Africa/Nouakchott",
    "iso:country":"MR",
    "wof:name":"Dernie",
    "wof:placetype":"locality"
},
  "geometry": {"coordinates":[-11.15819,15.52514],"type":"Point"}
}