{
  "type": "Feature",
  "properties": {
    "gn:admin1_code":"02",
    "gn:asciiname":"Kerfi",
    "gn:country_code":"MR",
    "gn:dem":183,
    "gn:feature_class":"P",
    "gn:feature_code":"PPL",
    "gn:name":"Kerfi",
    "gn:population":0,
    "gn:timezone":"Africa/Nouakchott",
    "iso:country":"MR",
    "wof:name":"Kerfi",
    "wof:placetype":"locality"
},
  "geometry": {"coordinates":[-9.48203,15.69471],"type":"Point"}
}