{
  "type": "Feature",
  "properties": {
    "gn:admin1_code":"02",
    "gn:asciiname":"Alaina",
    "gn:country_code":"MR",
    "gn:dem":154,
    "gn:feature_class":"P",
    "gn:feature_code":"PPL",
    "gn:name":"Ala\u00efna",
    "gn:population":0,
    "gn:timezone":"Africa/Nouakchott",
    "iso:country":"MR",
    "wof:name":"Alaina",
    "wof:placetype":"locality"
},
  "geometry": {"coordinates":[-10.46438,15.43949],"type":"Point"}
}