{
  "type": "Feature",
  "properties": {
    "gn:admin1_code":"02",
    "gn:asciiname":"Zreif el Azra",
    "gn:country_code":"MR",
    "gn:dem":205,
    "gn:feature_class":"P",
    "gn:feature_code":"PPL",
    "gn:name":"Zre\u00eff el Azra",
    "gn:population":0,
    "gn:timezone":"Africa/Nouakchott",
    "iso:country":"MR",
    "wof:name":"Zreif el Azra",
    "wof:placetype":"locality"
},
  "geometry": {"coordinates":[-9.50133,15.54965],"type":"Point"}
}