{
  "type": "Feature",
  "properties": {
    "gn:admin1_code":"04",
    "gn:asciiname":"Fimbo Paliba",
    "gn:country_code":"MR",
    "gn:dem":21,
    "gn:feature_class":"P",
    "gn:feature_code":"PPL",
    "gn:name":"Fimbo Paliba",
    "gn:population":0,
    "gn:timezone":"Africa/Nouakchott",
    "iso:country":"MR",
    "name:und_x_variant":[
        "Fimbo",
        "Fimbo Paliba"
    ],
    "wof:name":"Fimbo Paliba",
    "wof:placetype":"locality"
},
  "geometry": {"coordinates":[-12.88679,15.45504],"type":"Point"}
}