{
  "type": "Feature",
  "properties": {
    "gn:admin1_code":"10",
    "gn:asciiname":"Diala",
    "gn:country_code":"MR",
    "gn:dem":65,
    "gn:feature_class":"P",
    "gn:feature_code":"PPL",
    "gn:name":"Diala",
    "gn:population":0,
    "gn:timezone":"Africa/Nouakchott",
    "iso:country":"MR",
    "wof:name":"Diala",
    "wof:placetype":"locality"
},
  "geometry": {"coordinates":[-12.27256,15.25581],"type":"Point"}
}