{
  "type": "Feature",
  "properties": {
    "gn:admin1_code":"02",
    "gn:asciiname":"Kouroukere Beda",
    "gn:country_code":"MR",
    "gn:dem":194,
    "gn:feature_class":"P",
    "gn:feature_code":"PPL",
    "gn:name":"Kourouk\u00e9r\u00e9 B\u00e9da",
    "gn:population":0,
    "gn:timezone":"Africa/Nouakchott",
    "iso:country":"MR",
    "wof:name":"Kouroukere Beda",
    "wof:placetype":"locality"
},
  "geometry": {"coordinates":[-9.6485,15.51866],"type":"Point"}
}